{
  "title": "Pepe Unchained",
  "slug": "pepe-unchained",
  "symbol": "$PEPU",
  "description": "Pepe Unchained ($PEPU) breaks free from Ethereum's constraints with its own Layer 2 blockchain, offering blazing-fast meme coin transactions and revolutionary staking rewards. The next evolution of meme culture meets cutting-edge technology.",
  "affiliateLink": "https://cryptopresale.com/go/pepe-unchained",
  "raise": "$5,600,000", 
  "apy": "89%",
  "status": "Live",
  "progress": 94,
  "date": "2025-08-06",
  "category": "Meme L2",
  "participants": 34520,
  "endDate": "2025-08-12"
}